{
  "Products": [
    {
      "ProductID": "PROD001",
      "Category": "อาหาร",
      "ProductName": "สปาเกตตีคาโบนาร่า",
      "ProductPrice": "150",
      "Stock": "40",
      "Picture_Name": "spaghetti_carbonara"
    },
    {
      "ProductID": "PROD002",
      "Category": "อาหาร",
      "ProductName": "สลัดผักอโวคาโด",
      "ProductPrice": "95",
      "Stock": "36",
      "Picture_Name": "avocado_salad"
    },
    {
      "ProductID": "PROD003",
      "Category": "อาหาร",
      "ProductName": "แกงกะหรี่ญี่ปุ่น",
      "ProductPrice": "140",
      "Stock": "28",
      "Picture_Name": "japanese_curry"
    },
    {
      "ProductID": "PROD004",
      "Category": "อาหาร",
      "ProductName": "โอโคโนมิยากิ",
      "ProductPrice": "130",
      "Stock": "22",
      "Picture_Name": "okonomiyaki"
    },
    {
      "ProductID": "PROD005",
      "Category": "อาหาร",
      "ProductName": "ข้าวผัดเบคอน",
      "ProductPrice": "110",
      "Stock": "47",
      "Picture_Name": "bacon_fried_rice"
    },
    {
      "ProductID": "PROD006",
      "Category": "เครื่องดื่ม",
      "ProductName": "ลาเต้ร้อน",
      "ProductPrice": "65",
      "Stock": "60",
      "Picture_Name": "hot_latte"
    },
    {
      "ProductID": "PROD007",
      "Category": "เครื่องดื่ม",
      "ProductName": "ชาเขียวเย็น",
      "ProductPrice": "55",
      "Stock": "72",
      "Picture_Name": "iced_green_tea"
    },
    {
      "ProductID": "PROD008",
      "Category": "เครื่องดื่ม",
      "ProductName": "โกโก้ปั่น",
      "ProductPrice": "75",
      "Stock": "54",
      "Picture_Name": "cocoa_frappe"
    },
    {
      "ProductID": "PROD009",
      "Category": "เครื่องดื่ม",
      "ProductName": "น้ำผึ้งมะนาวโซดา",
      "ProductPrice": "70",
      "Stock": "48",
      "Picture_Name": "honey_lemon_soda"
    },
    {
      "ProductID": "PROD010",
      "Category": "เครื่องดื่ม",
      "ProductName": "ชามะลิเย็น",
      "ProductPrice": "50",
      "Stock": "63",
      "Picture_Name": "iced_jasmine_tea"
    },
    {
      "ProductID": "PROD011",
      "Category": "ของแมว",
      "ProductName": "ทูน่ากระป๋องสำหรับแมว",
      "ProductPrice": "45",
      "Stock": "52",
      "Picture_Name": "canned_tuna_for_cats"
    },
    {
      "ProductID": "PROD012",
      "Category": "ของแมว",
      "ProductName": "ขนมแมวเลียรสปลาโอ",
      "ProductPrice": "25",
      "Stock": "110",
      "Picture_Name": "tuna_cat_snack"
    },
    {
      "ProductID": "PROD013",
      "Category": "ของแมว",
      "ProductName": "ไก่อบแห้งหั่นชิ้น",
      "ProductPrice": "35",
      "Stock": "68",
      "Picture_Name": "dried_chicken_chunks"
    },
    {
      "ProductID": "PROD014",
      "Category": "ของแมว",
      "ProductName": "ปลาต้มบดสำหรับแมวเด็ก",
      "ProductPrice": "30",
      "Stock": "75",
      "Picture_Name": "mashed_fish_for_kittens"
    },
    {
      "ProductID": "PROD015",
      "Category": "ของแมว",
      "ProductName": "ขนมแมวรสชีส",
      "ProductPrice": "40",
      "Stock": "60",
      "Picture_Name": "cheese_flavored_cat_treats"
    }
  ]
}
